getgeo/__init__.py
getgeo/base.py
getgeo/geodata.py
getgeo_python-1.1.0.dist-info/LICENSE
getgeo_python-1.1.0.dist-info/METADATA
getgeo_python-1.1.0.dist-info/WHEEL
getgeo_python-1.1.0.dist-info/top_level.txt
getgeo_python-1.1.0.dist-info/RECORD
