Metadata-Version: 2.1
Name: getgeo-python
Version: 1.1.0
Summary: A python wrapper for the API provided by getgeoapi.com
Home-page: https://github.com/LoisaKitakaya/getgeo-python
Author: Loisa Kitakaya
Author-email: kitakayaloisa@gmail.com
License: UNKNOWN
Project-URL: Bug Tracker, https://github.com/LoisaKitakaya/getgeo-python/issues
Project-URL: Documentation, https://github.com/LoisaKitakaya/getgeo-python#readme
Platform: UNKNOWN
Classifier: Development Status :: 5 - Production/Stable
Classifier: Intended Audience :: Developers
Classifier: License :: OSI Approved :: MIT License
Classifier: Programming Language :: Python :: 3
Classifier: Operating System :: OS Independent
Requires-Python: >=3.6
License-File: LICENSE
Requires-Dist: requests (>=2.30.0)
